getpalette/Roboto-Medium.ttf
getpalette/__init__.py
getpalette/__main__.py
getpalette-1.0.7.dist-info/LICENSE
getpalette-1.0.7.dist-info/METADATA
getpalette-1.0.7.dist-info/WHEEL
getpalette-1.0.7.dist-info/entry_points.txt
getpalette-1.0.7.dist-info/top_level.txt
getpalette-1.0.7.dist-info/RECORD
