Metadata-Version: 2.1
Name: getpalette
Version: 1.0.7
Summary: Get color palette from images
Home-page: https://github.com/ssiyad/getpalette
Author: Sabu Siyad
Author-email: sabu.siyad.p@gmail.com
License: MIT
Platform: UNKNOWN
Requires-Dist: Pillow (==6.2.1)
Requires-Dist: matplotlib (==3.0.3)
Requires-Dist: scipy (==1.3.1)
Requires-Dist: pandas (==0.24.2)
